{
  "types": [
    {
      "name": "targetType",
      "kind": "object",
      "content": [
        {
          "name": "dayTimeDurations",
          "type": {
            "kind": "array",
            "content": [
              "dayTimeDurationObj"
            ]
          }
        }
      ]
    },
    {
      "name": "dayTimeDurationType",
      "kind": "atomic",
      "baseType": "dayTimeDuration"
    },
    {
      "name": "dayTimeDurationObj",
      "kind": "object",
      "content": [
        {
          "name": "integerValue",
          "type": "dayTimeDurationType",
          "default": 34
        },
        {
          "name": "stringValue",
          "type": "dayTimeDurationType",
          "default": "randomString"
        },
        {
          "name": "incorrectDayTimeDurationValue1",
          "type": "dayTimeDurationType",
          "default": "P-20M"
        },
        {
          "name": "incorrectDayTimeDurationValue2",
          "type": "dayTimeDurationType",
          "default": "PT15.S"
        },
        {
          "name": "incorrectDayTimeDurationValue3",
          "type": "dayTimeDurationType",
          "default": "P2Y6M5DT12H35M30S"
        },
        {
          "name": "nullValue",
          "type": "dayTimeDurationType",
          "default": null
        },
        {
          "name": "booleanValue",
          "type": "dayTimeDurationType",
          "default": false
        },
        {
          "name": "objectValue",
          "type": "dayTimeDurationType",
          "default": {
            "hello": "world!"
          }
        },
        {
          "name": "arrayValue",
          "type": "dayTimeDurationType",
          "default": [ "thisIsAString" ]
        }
      ]
    }
  ]
}
